qubox/__init__.py
qubox/cQED_experiments.py
qubox/cQED_programs.py
qubox/calibration.py
qubox/config_builder.py
qubox/config_template.py
qubox/gates.py
qubox/logger.py
qubox/program_manager.py
qubox/pulse_manager.py
qubox/qua_cQED_programs.py
qubox/sequence_builder.py
qubox-0.1.1.dist-info/METADATA
qubox-0.1.1.dist-info/WHEEL
qubox-0.1.1.dist-info/top_level.txt
qubox-0.1.1.dist-info/RECORD
